<?xml version="1.0" encoding="utf-8" ?>
<dwsync>
<file name="01.htm" server="protopopov.ru/public_html/pdd/" local="130197575843794499" remote="130197285000000000" Dst="0" />
<file name="01.jpg" server="protopopov.ru/public_html/pdd/" local="129826536560000000" remote="130187663400000000" Dst="0" />
<file name="010.htm" server="protopopov.ru/public_html/pdd/" local="130197524100774968" remote="130197285000000000" Dst="0" />
<file name="011.htm" server="protopopov.ru/public_html/pdd/" local="130197524100874973" remote="130197285000000000" Dst="0" />
<file name="02.htm" server="protopopov.ru/public_html/pdd/" local="130197575843924507" remote="130197285000000000" Dst="0" />
<file name="020.htm" server="protopopov.ru/public_html/pdd/" local="130197524101054984" remote="130197285000000000" Dst="0" />
<file name="021.htm" server="protopopov.ru/public_html/pdd/" local="130197524101154989" remote="130197285000000000" Dst="0" />
<file name="02.jpg" server="protopopov.ru/public_html/pdd/" local="129826536560000000" remote="130187663400000000" Dst="0" />
<file name="03.htm" server="protopopov.ru/public_html/pdd/" local="130197575844034513" remote="130197285000000000" Dst="0" />
<file name="03.jpg" server="protopopov.ru/public_html/pdd/" local="129826536560000000" remote="130187663400000000" Dst="0" />
<file name="030.htm" server="protopopov.ru/public_html/pdd/" local="130197524101365001" remote="130197285000000000" Dst="0" />
<file name="031.htm" server="protopopov.ru/public_html/pdd/" local="130197524101465007" remote="130197285000000000" Dst="0" />
<file name="04.htm" server="protopopov.ru/public_html/pdd/" local="130197575844144519" remote="130197285000000000" Dst="0" />
<file name="040.htm" server="protopopov.ru/public_html/pdd/" local="130197524101645017" remote="130197285000000000" Dst="0" />
<file name="04.jpg" server="protopopov.ru/public_html/pdd/" local="129826536560000000" remote="130187663400000000" Dst="0" />
<file name="041.htm" server="protopopov.ru/public_html/pdd/" local="130197524101755024" remote="130197285000000000" Dst="0" />
<file name="05.htm" server="protopopov.ru/public_html/pdd/" local="130197575844284527" remote="130197285000000000" Dst="0" />
<file name="050.htm" server="protopopov.ru/public_html/pdd/" local="130197524101925033" remote="130197285000000000" Dst="0" />
<file name="051.htm" server="protopopov.ru/public_html/pdd/" local="130197524102925091" remote="130197285000000000" Dst="0" />
<file name="05.jpg" server="protopopov.ru/public_html/pdd/" local="129826536560000000" remote="130187663400000000" Dst="0" />
<file name="06.htm" server="protopopov.ru/public_html/pdd/" local="130197575844434536" remote="130197285000000000" Dst="0" />
<file name="06.jpg" server="protopopov.ru/public_html/pdd/" local="129826536560000000" remote="130187663400000000" Dst="0" />
<file name="060.htm" server="protopopov.ru/public_html/pdd/" local="130197524103145103" remote="130197285000000000" Dst="0" />
<file name="061.htm" server="protopopov.ru/public_html/pdd/" local="130197524103365116" remote="130197285000000000" Dst="0" />
<file name="07.htm" server="protopopov.ru/public_html/pdd/" local="130197575844544542" remote="130197285000000000" Dst="0" />
<file name="070.htm" server="protopopov.ru/public_html/pdd/" local="130197503860517291" remote="130197285000000000" Dst="0" />
<file name="071.htm" server="protopopov.ru/public_html/pdd/" local="130197503860687301" remote="130197285000000000" Dst="0" />
<file name="08.htm" server="protopopov.ru/public_html/pdd/" local="130197575844684550" remote="130197285000000000" Dst="0" />
<file name="080.htm" server="protopopov.ru/public_html/pdd/" local="130197524103605130" remote="130197285000000000" Dst="0" />
<file name="08.jpg" server="protopopov.ru/public_html/pdd/" local="129826536560000000" remote="130187664000000000" Dst="0" />
<file name="081.htm" server="protopopov.ru/public_html/pdd/" local="130197524103705135" remote="130197285000000000" Dst="0" />
<file name="09.htm" server="protopopov.ru/public_html/pdd/" local="130197575844794556" remote="130197285000000000" Dst="0" />
<file name="091.htm" server="protopopov.ru/public_html/pdd/" local="130197524104065156" remote="130197285000000000" Dst="0" />
<file name="090.htm" server="protopopov.ru/public_html/pdd/" local="130197524103885146" remote="130197285000000000" Dst="0" />
<file name="09.jpg" server="protopopov.ru/public_html/pdd/" local="129826536560000000" remote="130187664000000000" Dst="0" />
<file name="10.htm" server="protopopov.ru/public_html/pdd/" local="130197575844924564" remote="130197285000000000" Dst="0" />
<file name="100.htm" server="protopopov.ru/public_html/pdd/" local="130197524104265167" remote="130197285000000000" Dst="0" />
<file name="101.htm" server="protopopov.ru/public_html/pdd/" local="130197524104365173" remote="130197285000000000" Dst="0" />
<file name="10.jpg" server="protopopov.ru/public_html/pdd/" local="129826536560000000" remote="130187664000000000" Dst="0" />
<file name="11.htm" server="protopopov.ru/public_html/pdd/" local="130197575845054571" remote="130197285000000000" Dst="0" />
<file name="110.htm" server="protopopov.ru/public_html/pdd/" local="130197524104585186" remote="130197285600000000" Dst="0" />
<file name="11.jpg" server="protopopov.ru/public_html/pdd/" local="129826536560000000" remote="130187664000000000" Dst="0" />
<file name="111.htm" server="protopopov.ru/public_html/pdd/" local="130197524104655190" remote="130197285600000000" Dst="0" />
<file name="12.htm" server="protopopov.ru/public_html/pdd/" local="130197575845194579" remote="130197285600000000" Dst="0" />
<file name="12.jpg" server="protopopov.ru/public_html/pdd/" local="129826536560000000" remote="130187664000000000" Dst="0" />
<file name="120.htm" server="protopopov.ru/public_html/pdd/" local="130197524104835200" remote="130197285600000000" Dst="0" />
<file name="121.htm" server="protopopov.ru/public_html/pdd/" local="130197524104935206" remote="130197285600000000" Dst="0" />
<file name="13.htm" server="protopopov.ru/public_html/pdd/" local="130197575845324587" remote="130197285600000000" Dst="0" />
<file name="130.htm" server="protopopov.ru/public_html/pdd/" local="130197524105115216" remote="130197285600000000" Dst="0" />
<file name="131.htm" server="protopopov.ru/public_html/pdd/" local="130197524105245223" remote="130197285600000000" Dst="0" />
<file name="13.jpg" server="protopopov.ru/public_html/pdd/" local="129826536560000000" remote="130187664000000000" Dst="0" />
<file name="14.htm" server="protopopov.ru/public_html/pdd/" local="130197575845454594" remote="130197285600000000" Dst="0" />
<file name="140.htm" server="protopopov.ru/public_html/pdd/" local="130197524105445235" remote="130197285600000000" Dst="0" />
<file name="14.jpg" server="protopopov.ru/public_html/pdd/" local="129826536560000000" remote="130187664000000000" Dst="0" />
<file name="141.htm" server="protopopov.ru/public_html/pdd/" local="130197524105545241" remote="130197285600000000" Dst="0" />
<file name="15.htm" server="protopopov.ru/public_html/pdd/" local="130197575845584602" remote="130197285600000000" Dst="0" />
<file name="150.htm" server="protopopov.ru/public_html/pdd/" local="130197524105755253" remote="130197285600000000" Dst="0" />
<file name="15.jpg" server="protopopov.ru/public_html/pdd/" local="129826536560000000" remote="130187664000000000" Dst="0" />
<file name="151.htm" server="protopopov.ru/public_html/pdd/" local="130197524105855258" remote="130197285600000000" Dst="0" />
<file name="16.htm" server="protopopov.ru/public_html/pdd/" local="130197575845724610" remote="130197285600000000" Dst="0" />
<file name="160.htm" server="protopopov.ru/public_html/pdd/" local="130197524106065270" remote="130197285600000000" Dst="0" />
<file name="16.jpg" server="protopopov.ru/public_html/pdd/" local="129826536560000000" remote="130187664000000000" Dst="0" />
<file name="161.htm" server="protopopov.ru/public_html/pdd/" local="130197524106165276" remote="130197285600000000" Dst="0" />
<file name="17.htm" server="protopopov.ru/public_html/pdd/" local="130197575845864618" remote="130197285600000000" Dst="0" />
<file name="170.htm" server="protopopov.ru/public_html/pdd/" local="130197503865177558" remote="130197285600000000" Dst="0" />
<file name="171.htm" server="protopopov.ru/public_html/pdd/" local="130197503865277563" remote="130197285600000000" Dst="0" />
<file name="18.htm" server="protopopov.ru/public_html/pdd/" local="130197575846004626" remote="130197285600000000" Dst="0" />
<file name="180.htm" server="protopopov.ru/public_html/pdd/" local="130197503865477575" remote="130197285600000000" Dst="0" />
<file name="181.htm" server="protopopov.ru/public_html/pdd/" local="130197503865577581" remote="130197285600000000" Dst="0" />
<file name="19.htm" server="protopopov.ru/public_html/pdd/" local="130197575846134633" remote="130197285600000000" Dst="0" />
<file name="190.htm" server="protopopov.ru/public_html/pdd/" local="130197503865787593" remote="130197285600000000" Dst="0" />
<file name="191.htm" server="protopopov.ru/public_html/pdd/" local="130197503865887598" remote="130197285600000000" Dst="0" />
<file name="20.htm" server="protopopov.ru/public_html/pdd/" local="130197575846244639" remote="130197285600000000" Dst="0" />
<file name="200.htm" server="protopopov.ru/public_html/pdd/" local="130197574577052046" remote="130197285600000000" Dst="0" />
<file name="201.htm" server="protopopov.ru/public_html/pdd/" local="130197574577152051" remote="130197285600000000" Dst="0" />
</dwsync>