<?xml version="1.0" encoding="utf-8" ?>
<dwsync>
<file name="010.htm" server="protopopov.ru/public_html/pdd/" local="130197503542409096" remote="130197266400000000" Dst="0" />
<file name="01.htm" server="protopopov.ru/public_html/pdd/" local="130197575717457273" remote="130197266400000000" Dst="0" />
<file name="011.htm" server="protopopov.ru/public_html/pdd/" local="130197503542499102" remote="130197266400000000" Dst="0" />
<file name="02.htm" server="protopopov.ru/public_html/pdd/" local="130197575717577280" remote="130197266400000000" Dst="0" />
<file name="020.htm" server="protopopov.ru/public_html/pdd/" local="130197523882202466" remote="130197266400000000" Dst="0" />
<file name="02.jpg" server="protopopov.ru/public_html/pdd/" local="129826536570000000" remote="130187643600000000" Dst="0" />
<file name="021.htm" server="protopopov.ru/public_html/pdd/" local="130197523882292471" remote="130197266400000000" Dst="0" />
<file name="03.htm" server="protopopov.ru/public_html/pdd/" local="130197575717707287" remote="130197266400000000" Dst="0" />
<file name="030.htm" server="protopopov.ru/public_html/pdd/" local="130197523882482482" remote="130197266400000000" Dst="0" />
<file name="031.htm" server="protopopov.ru/public_html/pdd/" local="130197523882582488" remote="130197266400000000" Dst="0" />
<file name="03.jpg" server="protopopov.ru/public_html/pdd/" local="129826536570000000" remote="130187643600000000" Dst="0" />
<file name="04.htm" server="protopopov.ru/public_html/pdd/" local="130197575717837295" remote="130197266400000000" Dst="0" />
<file name="04.jpg" server="protopopov.ru/public_html/pdd/" local="129826536570000000" remote="130187643600000000" Dst="0" />
<file name="040.htm" server="protopopov.ru/public_html/pdd/" local="130197523882772499" remote="130197266400000000" Dst="0" />
<file name="041.htm" server="protopopov.ru/public_html/pdd/" local="130197523882862504" remote="130197266400000000" Dst="0" />
<file name="05.htm" server="protopopov.ru/public_html/pdd/" local="130197575717977303" remote="130197266400000000" Dst="0" />
<file name="050.htm" server="protopopov.ru/public_html/pdd/" local="130197523883052515" remote="130197266400000000" Dst="0" />
<file name="05.jpg" server="protopopov.ru/public_html/pdd/" local="129826536570000000" remote="130187643600000000" Dst="0" />
<file name="051.htm" server="protopopov.ru/public_html/pdd/" local="130197523883142520" remote="130197266400000000" Dst="0" />
<file name="06.htm" server="protopopov.ru/public_html/pdd/" local="130197575718117311" remote="130197266400000000" Dst="0" />
<file name="060.htm" server="protopopov.ru/public_html/pdd/" local="130197523883332531" remote="130197266400000000" Dst="0" />
<file name="06.jpg" server="protopopov.ru/public_html/pdd/" local="129826536570000000" remote="130187643600000000" Dst="0" />
<file name="061.htm" server="protopopov.ru/public_html/pdd/" local="130197523883432536" remote="130197266400000000" Dst="0" />
<file name="07.htm" server="protopopov.ru/public_html/pdd/" local="130197575718267319" remote="130197266400000000" Dst="0" />
<file name="070.htm" server="protopopov.ru/public_html/pdd/" local="130197523883642548" remote="130197266400000000" Dst="0" />
<file name="071.htm" server="protopopov.ru/public_html/pdd/" local="130197523883742554" remote="130197266400000000" Dst="0" />
<file name="07.jpg" server="protopopov.ru/public_html/pdd/" local="129826536570000000" remote="130187643600000000" Dst="0" />
<file name="08.htm" server="protopopov.ru/public_html/pdd/" local="130197575718407327" remote="130197266400000000" Dst="0" />
<file name="080.htm" server="protopopov.ru/public_html/pdd/" local="130197523883952566" remote="130197266400000000" Dst="0" />
<file name="081.htm" server="protopopov.ru/public_html/pdd/" local="130197523884052572" remote="130197266400000000" Dst="0" />
<file name="08.jpg" server="protopopov.ru/public_html/pdd/" local="129826536570000000" remote="130187644200000000" Dst="0" />
<file name="09.htm" server="protopopov.ru/public_html/pdd/" local="130197575718547335" remote="130197266400000000" Dst="0" />
<file name="09.jpg" server="protopopov.ru/public_html/pdd/" local="129826536570000000" remote="130187644200000000" Dst="0" />
<file name="090.htm" server="protopopov.ru/public_html/pdd/" local="130197523884252583" remote="130197266400000000" Dst="0" />
<file name="091.htm" server="protopopov.ru/public_html/pdd/" local="130197523884352589" remote="130197266400000000" Dst="0" />
<file name="10.htm" server="protopopov.ru/public_html/pdd/" local="130197575718677343" remote="130197266400000000" Dst="0" />
<file name="100.htm" server="protopopov.ru/public_html/pdd/" local="130197503544969243" remote="130197266400000000" Dst="0" />
<file name="101.htm" server="protopopov.ru/public_html/pdd/" local="130197503545059248" remote="130197266400000000" Dst="0" />
<file name="11.htm" server="protopopov.ru/public_html/pdd/" local="130197575718817351" remote="130197266400000000" Dst="0" />
<file name="110.htm" server="protopopov.ru/public_html/pdd/" local="130197523884602603" remote="130197266400000000" Dst="0" />
<file name="11.jpg" server="protopopov.ru/public_html/pdd/" local="129826536570000000" remote="130187644200000000" Dst="0" />
<file name="111.htm" server="protopopov.ru/public_html/pdd/" local="130197523884702609" remote="130197266400000000" Dst="0" />
<file name="12.htm" server="protopopov.ru/public_html/pdd/" local="130197575718957359" remote="130197266400000000" Dst="0" />
<file name="120.htm" server="protopopov.ru/public_html/pdd/" local="130197523884912621" remote="130197266400000000" Dst="0" />
<file name="121.htm" server="protopopov.ru/public_html/pdd/" local="130197523885022627" remote="130197266400000000" Dst="0" />
<file name="12.jpg" server="protopopov.ru/public_html/pdd/" local="129826536570000000" remote="130187644200000000" Dst="0" />
<file name="13.htm" server="protopopov.ru/public_html/pdd/" local="130197575719087366" remote="130197266400000000" Dst="0" />
<file name="130.htm" server="protopopov.ru/public_html/pdd/" local="130197523885222639" remote="130197266400000000" Dst="0" />
<file name="13.jpg" server="protopopov.ru/public_html/pdd/" local="129826536570000000" remote="130187644200000000" Dst="0" />
<file name="131.htm" server="protopopov.ru/public_html/pdd/" local="130197523885322645" remote="130197266400000000" Dst="0" />
<file name="14.htm" server="protopopov.ru/public_html/pdd/" local="130197575719447387" remote="130197266400000000" Dst="0" />
<file name="140.htm" server="protopopov.ru/public_html/pdd/" local="130197523885822673" remote="130197266400000000" Dst="0" />
<file name="14.jpg" server="protopopov.ru/public_html/pdd/" local="129826536570000000" remote="130187644200000000" Dst="0" />
<file name="141.htm" server="protopopov.ru/public_html/pdd/" local="130197523885932679" remote="130197266400000000" Dst="0" />
<file name="15.htm" server="protopopov.ru/public_html/pdd/" local="130197575719577394" remote="130197266400000000" Dst="0" />
<file name="150.htm" server="protopopov.ru/public_html/pdd/" local="130197523886152692" remote="130197266400000000" Dst="0" />
<file name="15.jpg" server="protopopov.ru/public_html/pdd/" local="129826536570000000" remote="130187644200000000" Dst="0" />
<file name="151.htm" server="protopopov.ru/public_html/pdd/" local="130197523886252698" remote="130197266400000000" Dst="0" />
<file name="16.htm" server="protopopov.ru/public_html/pdd/" local="130197575719707402" remote="130197266400000000" Dst="0" />
<file name="16.jpg" server="protopopov.ru/public_html/pdd/" local="129826536570000000" remote="130187644200000000" Dst="0" />
<file name="160.htm" server="protopopov.ru/public_html/pdd/" local="130197523886452709" remote="130197266400000000" Dst="0" />
<file name="161.htm" server="protopopov.ru/public_html/pdd/" local="130197523886552715" remote="130197266400000000" Dst="0" />
<file name="17.htm" server="protopopov.ru/public_html/pdd/" local="130197575719837409" remote="130197266400000000" Dst="0" />
<file name="170.htm" server="protopopov.ru/public_html/pdd/" local="130197503546949356" remote="130197266400000000" Dst="0" />
<file name="18.htm" server="protopopov.ru/public_html/pdd/" local="130197575719967417" remote="130197266400000000" Dst="0" />
<file name="171.htm" server="protopopov.ru/public_html/pdd/" local="130197503547039361" remote="130197266400000000" Dst="0" />
<file name="180.htm" server="protopopov.ru/public_html/pdd/" local="130197503547219372" remote="130197266400000000" Dst="0" />
<file name="181.htm" server="protopopov.ru/public_html/pdd/" local="130197503547309377" remote="130197266400000000" Dst="0" />
<file name="19.htm" server="protopopov.ru/public_html/pdd/" local="130197575720097424" remote="130197266400000000" Dst="0" />
<file name="190.htm" server="protopopov.ru/public_html/pdd/" local="130197503547499388" remote="130197266400000000" Dst="0" />
<file name="191.htm" server="protopopov.ru/public_html/pdd/" local="130197503547589393" remote="130197266400000000" Dst="0" />
<file name="20.htm" server="protopopov.ru/public_html/pdd/" local="130197575720227431" remote="130197266400000000" Dst="0" />
<file name="200.htm" server="protopopov.ru/public_html/pdd/" local="130197574386481146" remote="130197266400000000" Dst="0" />
<file name="201.htm" server="protopopov.ru/public_html/pdd/" local="130197574387131183" remote="130197266400000000" Dst="0" />
</dwsync>